syncweb-0.0.17.dist-info/METADATA
syncweb-0.0.17.dist-info/WHEEL
syncweb-0.0.17.dist-info/entry_points.txt
syncweb-0.0.17.dist-info/licenses/LICENSE
syncweb/__init__.py
syncweb/__main__.py
syncweb/cli.py
syncweb/cmd_utils.py
syncweb/cmds/automatic.py
syncweb/cmds/devices.py
syncweb/cmds/download.py
syncweb/cmds/find.py
syncweb/cmds/folders.py
syncweb/cmds/ls.py
syncweb/cmds/sort.py
syncweb/cmds/stat.py
syncweb/config.py
syncweb/consts.py
syncweb/ensure.py
syncweb/log_utils.py
syncweb/str_utils.py
syncweb/syncthing.py
syncweb/syncweb.py
syncweb-0.0.17.dist-info/RECORD
