Metadata-Version: 2.1
Name: syncweb
Version: 0.0.17
Summary: Syncweb: an offline-first distributed web
License: Copyright 2025 Syncweb Authors
Project-URL: documentation, https://github.com/chapmanjacobd/syncweb-py#usage
Project-URL: homepage, https://github.com/chapmanjacobd/syncweb-py#readme
Project-URL: repository, https://github.com/chapmanjacobd/syncweb-py/
Requires-Python: >=3.11
Requires-Dist: idna
Requires-Dist: humanize
Requires-Dist: tabulate
Requires-Dist: ipython>=9
Requires-Dist: requests>=2
Provides-Extra: dev
Requires-Dist: black; extra == "dev"
Requires-Dist: isort; extra == "dev"
Requires-Dist: ssort; extra == "dev"
Provides-Extra: test
Requires-Dist: ruff; extra == "test"
Requires-Dist: pytest; extra == "test"
